{"bad_queries": {"Immediate (< 1 day) for SUSE QA": {"url": "https://progress.opensuse.org/issues?project_id=46&utf8=%E2%9C%93&set_filter=1&sort=updated_on%3Adesc&f%5B%5D=priority_id&op%5Bpriority_id%5D=%3D&v%5Bpriority_id%5D%5B%5D=7&f%5B%5D=status_id&op%5Bstatus_id%5D=o&f%5B%5D=updated_on&op%5Bupdated_on%5D=%3Ct-&v%5Bupdated_on%5D%5B%5D=1&f%5B%5D=subproject_id&op%5Bsubproject_id%5D=*&f%5B%5D=child_id&op%5Bchild_id%5D=%21*&f%5B%5D=&c%5B%5D=subject&c%5B%5D=status&c%5B%5D=assigned_to&c%5B%5D=due_date&c%5B%5D=updated_on&c%5B%5D=category&group_by=&t%5B%5D=", "issue_count": 3, "limits": "<1"}, "Urgent (< 1 week) for SUSE QA": {"url": "https://progress.opensuse.org/issues?project_id=46&utf8=%E2%9C%93&set_filter=1&sort=updated_on%3Adesc&f%5B%5D=priority_id&op%5Bpriority_id%5D=%3D&v%5Bpriority_id%5D%5B%5D=6&f%5B%5D=status_id&op%5Bstatus_id%5D=o&f%5B%5D=updated_on&op%5Bupdated_on%5D=%3Ct-&v%5Bupdated_on%5D%5B%5D=7&f%5B%5D=subproject_id&op%5Bsubproject_id%5D=*&f%5B%5D=child_id&op%5Bchild_id%5D=%21*&f%5B%5D=&c%5B%5D=subject&c%5B%5D=project&c%5B%5D=status&c%5B%5D=assigned_to&c%5B%5D=due_date&c%5B%5D=updated_on&c%5B%5D=category&group_by=&t%5B%5D=", "issue_count": 2, "limits": "<1"}, "High (< 1 month)": {"url": "https://progress.opensuse.org/issues?project_id=36&utf8=%E2%9C%93&set_filter=1&sort=updated_on%3Adesc&f%5B%5D=priority_id&op%5Bpriority_id%5D=%3D&v%5Bpriority_id%5D%5B%5D=5&f%5B%5D=status_id&op%5Bstatus_id%5D=o&f%5B%5D=updated_on&op%5Bupdated_on%5D=%3Ct-&v%5Bupdated_on%5D%5B%5D=30&f%5B%5D=subproject_id&op%5Bsubproject_id%5D=*&f%5B%5D=child_id&op%5Bchild_id%5D=%21*&f%5B%5D=&c%5B%5D=subject&c%5B%5D=project&c%5B%5D=status&c%5B%5D=assigned_to&c%5B%5D=due_date&c%5B%5D=updated_on&c%5B%5D=category&group_by=&t%5B%5D=", "issue_count": 25, "limits": "<1"}, "Normal (< 1 year)": {"url": "https://progress.opensuse.org/issues?project_id=36&utf8=%E2%9C%93&set_filter=1&sort=updated_on%3Adesc&f%5B%5D=priority_id&op%5Bpriority_id%5D=%3D&v%5Bpriority_id%5D%5B%5D=4&f%5B%5D=status_id&op%5Bstatus_id%5D=o&f%5B%5D=updated_on&op%5Bupdated_on%5D=%3Ct-&v%5Bupdated_on%5D%5B%5D=365&f%5B%5D=subproject_id&op%5Bsubproject_id%5D=*&f%5B%5D=child_id&op%5Bchild_id%5D=%21*&f%5B%5D=&c%5B%5D=subject&c%5B%5D=project&c%5B%5D=status&c%5B%5D=assigned_to&c%5B%5D=due_date&c%5B%5D=updated_on&c%5B%5D=category&group_by=&t%5B%5D=", "issue_count": 381, "limits": "<1"}, "Within due-date (10 days)": {"url": "https://progress.opensuse.org/issues?project_id=36&utf8=%E2%9C%93&set_filter=1&sort=updated_on%3Adesc&f%5B%5D=status_id&op%5Bstatus_id%5D=o&f%5B%5D=subproject_id&op%5Bsubproject_id%5D=*&f%5B%5D=due_date&op%5Bdue_date%5D=%3Ct-&v%5Bdue_date%5D%5B%5D=10&f%5B%5D=last_updated_by&op%5Blast_updated_by%5D=%21&v%5Blast_updated_by%5D%5B%5D=40859&f%5B%5D=&c%5B%5D=subject&c%5B%5D=project&c%5B%5D=status&c%5B%5D=assigned_to&c%5B%5D=due_date&c%5B%5D=updated_on&c%5B%5D=category&group_by=&t%5B%5D=", "issue_count": 3, "limits": "<1"}}, "updated": "2024-03-11T22:26:12.569848"}